garmindb/GarminConnectConfig.json.example
garmindb/__init__.py
garmindb/activities_fit_data.py
garmindb/activity_fit_file_processor.py
garmindb/activity_fit_plugin_base.py
garmindb/analyze.py
garmindb/checkup.py
garmindb/copy.py
garmindb/download.py
garmindb/export_activities.py
garmindb/fit_data.py
garmindb/fit_file_processor.py
garmindb/garmin_connect_config_manager.py
garmindb/garmin_connect_enums.py
garmindb/garmin_json_data.py
garmindb/garmin_tcx_data.py
garmindb/import_monitoring.py
garmindb/monitoring_fit_file_processor.py
garmindb/monitoring_fit_plugin_base.py
garmindb/open_with_basecamp.py
garmindb/open_with_google_earth.py
garmindb/plugin_base.py
garmindb/plugin_manager.py
garmindb/sleep_fit_file_processor.py
garmindb/statistics.py
garmindb/tcx.py
garmindb/version.py
garmindb/version_info.py
garmindb/fitbitdb/__init__.py
garmindb/fitbitdb/analyze.py
garmindb/fitbitdb/fitbit_db.py
garmindb/fitbitdb/import_csv.py
garmindb/garmindb/__init__.py
garmindb/garmindb/activities_db.py
garmindb/garmindb/garmin_db.py
garmindb/garmindb/garmin_summary_db.py
garmindb/garmindb/monitoring_db.py
garmindb/mshealthdb/__init__.py
garmindb/mshealthdb/analyze.py
garmindb/mshealthdb/import_csv.py
garmindb/mshealthdb/mshealth_db.py
garmindb/summarydb/__init__.py
garmindb/summarydb/summary_base.py
garmindb/summarydb/summary_db.py
garmindb-3.6.7.data/scripts/fitbit.py
garmindb-3.6.7.data/scripts/garmindb_bug_report.py
garmindb-3.6.7.data/scripts/garmindb_checkup.py
garmindb-3.6.7.data/scripts/garmindb_cli.py
garmindb-3.6.7.data/scripts/mshealth.py
garmindb-3.6.7.dist-info/licenses/LICENSE
garmindb-3.6.7.dist-info/METADATA
garmindb-3.6.7.dist-info/WHEEL
garmindb-3.6.7.dist-info/top_level.txt
garmindb-3.6.7.dist-info/RECORD
