Metadata-Version: 2.4
Name: GarminDb
Version: 3.6.7
Summary: Garmin Connect download and analysis
Home-page: https://github.com/tcgoetz/GarminDB
Author: Tom Goetz
License: GPL
Project-URL: Homepage, https://github.com/tcgoetz/GarminDB
Project-URL: Repository, https://github.com/tcgoetz/GarminDB
Project-URL: Issues, https://github.com/tcgoetz/GarminDB/issues
Project-URL: Changelog, https://github.com/tcgoetz/GarminDB/releases
Keywords: garmin,garmin connect
Classifier: Development Status :: 5 - Production/Stable
Classifier: License :: OSI Approved :: GNU General Public License v2 (GPLv2)
Classifier: Programming Language :: Python :: 3.10
Classifier: Programming Language :: Python :: 3.11
Classifier: Programming Language :: Python :: 3.12
Classifier: Programming Language :: Python :: 3.13
Classifier: Operating System :: MacOS :: MacOS X
Classifier: Operating System :: Microsoft :: Windows
Classifier: Operating System :: POSIX :: Linux
Classifier: Operating System :: OS Independent
Requires-Python: >=3.0
License-File: LICENSE
Requires-Dist: cached-property==1.5.2
Requires-Dist: fitfile>=1.1.11
Requires-Dist: garth==0.5.19
Requires-Dist: idbutils>=1.1.0
Requires-Dist: python-dateutil==2.9.0.post0
Requires-Dist: sqlalchemy==2.0.41
Requires-Dist: tcxfile>=1.0.4
Requires-Dist: tornado>=6.4.2
Requires-Dist: tqdm==4.66.5
Dynamic: home-page
Dynamic: license-file
Dynamic: requires-python
